bbm/__init__.py
bbm/constants.py
bbm/exceptions.py
bbm/kafka_extension.py
bbm/reporter.py
bbm/utils.py
bbm-0.0.12.dist-info/METADATA
bbm-0.0.12.dist-info/WHEEL
bbm-0.0.12.dist-info/licenses/LICENSE
bbm-0.0.12.dist-info/RECORD
