Metadata-Version: 2.1
Name: bbm
Version: 0.0.12
Summary: 📊 Buzzni Batch process Monitor.
Project-URL: homepage, https://github.com/buzzni/bbm
Project-URL: bug-tracker, https://github.com/buzzni/bbm/issues
Author-email: damonbuzzni <damon@buzzni.com>
License-Expression: MIT
License-File: LICENSE
Classifier: License :: OSI Approved :: MIT License
Classifier: Programming Language :: Python
Classifier: Programming Language :: Python :: 3
Classifier: Programming Language :: Python :: 3 :: Only
Classifier: Programming Language :: Python :: 3.7
Classifier: Programming Language :: Python :: 3.8
Classifier: Programming Language :: Python :: 3.9
Classifier: Programming Language :: Python :: 3.10
Classifier: Programming Language :: Python :: 3.11
Classifier: Topic :: Software Development :: Libraries :: Python Modules
Classifier: Typing :: Typed
Requires-Python: >=3.7.0
Requires-Dist: prettytable
Requires-Dist: pytz
Requires-Dist: requests
Provides-Extra: dev
Requires-Dist: pytest; extra == 'dev'
Requires-Dist: twine; extra == 'dev'
Provides-Extra: kafka
Requires-Dist: confluent-kafka>=1.6.0; extra == 'kafka'
Provides-Extra: test
Requires-Dist: black; extra == 'test'
Requires-Dist: isort; extra == 'test'
Requires-Dist: pytest; extra == 'test'
Requires-Dist: requests-mock; extra == 'test'
